kotlin version: 2.0.21
error message: org.jetbrains.kotlin.codegen.CompilationException: Back-end (JVM) Internal error: Couldn't transform method node:
EditAlarmScreen (JLcom/codzuregroup/daycall/ui/AlarmViewModel;Lkotlin/jvm/functions/Function0;Lkotlin/jvm/functions/Function1;Lkotlin/jvm/functions/Function1;Landroidx/compose/runtime/Composer;I)V:
  @Landroidx/compose/runtime/Composable;() // invisible
  @Landroidx/compose/runtime/ComposableTarget;(applier="androidx.compose.ui.UiComposable") // invisible
    // annotable parameter count: 7 (visible)
    // annotable parameter count: 7 (invisible)
    @Lorg/jetbrains/annotations/NotNull;() // invisible, parameter 1
    @Lorg/jetbrains/annotations/NotNull;() // invisible, parameter 2
    @Lorg/jetbrains/annotations/NotNull;() // invisible, parameter 3
    @Lorg/jetbrains/annotations/NotNull;() // invisible, parameter 4
    @Lorg/jetbrains/annotations/Nullable;() // invisible, parameter 5
   L0
    ALOAD 2
    LDC "viewModel"
    INVOKESTATIC kotlin/jvm/internal/Intrinsics.checkNotNullParameter (Ljava/lang/Object;Ljava/lang/String;)V
    ALOAD 2
    INVOKESTATIC kotlin/jvm/internal/$PseudoInsn.AS_NOT_NULL (Ljava/lang/Object;)Ljava/lang/Object;
    ASTORE 2
    ALOAD 3
    LDC "onBackPressed"
    INVOKESTATIC kotlin/jvm/internal/Intrinsics.checkNotNullParameter (Ljava/lang/Object;Ljava/lang/String;)V
    ALOAD 3
    INVOKESTATIC kotlin/jvm/internal/$PseudoInsn.AS_NOT_NULL (Ljava/lang/Object;)Ljava/lang/Object;
    ASTORE 3
    ALOAD 4
    LDC "onSaveAlarm"
    INVOKESTATIC kotlin/jvm/internal/Intrinsics.checkNotNullParameter (Ljava/lang/Object;Ljava/lang/String;)V
    ALOAD 4
    INVOKESTATIC kotlin/jvm/internal/$PseudoInsn.AS_NOT_NULL (Ljava/lang/Object;)Ljava/lang/Object;
    ASTORE 4
    ALOAD 5
    LDC "onDeleteAlarm"
    INVOKESTATIC kotlin/jvm/internal/Intrinsics.checkNotNullParameter (Ljava/lang/Object;Ljava/lang/String;)V
    ALOAD 5
    INVOKESTATIC kotlin/jvm/internal/$PseudoInsn.AS_NOT_NULL (Ljava/lang/Object;)Ljava/lang/Object;
    ASTORE 5
   L1
    LINENUMBER 77 L1
    ALOAD 6
    LDC -79810864
    INVOKEINTERFACE androidx/compose/runtime/Composer.startRestartGroup (I)Landroidx/compose/runtime/Composer; (itf)
    ASTORE 6
    ALOAD 6
    LDC "C(EditAlarmScreen)P(!1,4!1,3)77@3368L34,78@3431L34,79@3490L30,80@3547L30,81@3600L31,82@3657L44,83@3726L36,84@3784L33,85@3842L47,87@3926L7,88@3960L49,89@4059L29,100@4508L370,100@4484L394,116@4992L2243,172@7242L12631,113@4884L14989,527@22436L28,541@22972L444,556@23446L175,526@22392L1239:EditAlarmScreen.kt#3vhqwj"
    INVOKESTATIC androidx/compose/runtime/ComposerKt.sourceInformation (Landroidx/compose/runtime/Composer;Ljava/lang/String;)V
    ILOAD 7
    ISTORE 8
   L2
    ILOAD 7
    BIPUSH 6
    IAND
    IFNE L3
    ILOAD 8
    ALOAD 6
    LLOAD 0
    INVOKEINTERFACE androidx/compose/runtime/Composer.changed (J)Z (itf)
    IFEQ L4
    ICONST_4
    GOTO L5
   L4
    ICONST_2
   L5
    IOR
    ISTORE 8
   L3
    ILOAD 7
    BIPUSH 48
    IAND
    IFNE L6
    ILOAD 8
    ALOAD 6
    ALOAD 2
    INVOKEINTERFACE androidx/compose/runtime/Composer.changedInstance (Ljava/lang/Object;)Z (itf)
    IFEQ L7
    BIPUSH 32
    GOTO L8
   L7
    BIPUSH 16
   L8
    IOR
    ISTORE 8
   L6
    ILOAD 7
    SIPUSH 384
    IAND
    IFNE L9
    ILOAD 8
    ALOAD 6
    ALOAD 3
    INVOKEINTERFACE androidx/compose/runtime/Composer.changedInstance (Ljava/lang/Object;)Z (itf)
    IFEQ L10
    SIPUSH 256
    GOTO L11
   L10
    SIPUSH 128
   L11
    IOR
    ISTORE 8
   L9
    ILOAD 7
    SIPUSH 3072
    IAND
    IFNE L12
    ILOAD 8
    ALOAD 6
    ALOAD 4
    INVOKEINTERFACE androidx/compose/runtime/Composer.changedInstance (Ljava/lang/Object;)Z (itf)
    IFEQ L13
    SIPUSH 2048
    GOTO L14
   L13
    SIPUSH 1024
   L14
    IOR
    ISTORE 8
   L12
    ILOAD 7
    SIPUSH 24576
    IAND
    IFNE L15
    ILOAD 8
    ALOAD 6
    ALOAD 5
    INVOKEINTERFACE androidx/compose/runtime/Composer.changedInstance (Ljava/lang/Object;)Z (itf)
    IFEQ L16
    SIPUSH 16384
    GOTO L17
   L16
    SIPUSH 8192
   L17
    IOR
    ISTORE 8
   L15
    ILOAD 8
    SIPUSH 9363
    IAND
    SIPUSH 9362
    IF_ICMPNE L18
    ALOAD 6
    INVOKEINTERFACE androidx/compose/runtime/Composer.getSkipping ()Z (itf)
    IFNE L19
   L18
    INVOKESTATIC androidx/compose/runtime/ComposerKt.isTraceInProgress ()Z
    IFEQ L20
    LDC -79810864
    ILOAD 8
    ICONST_M1
    LDC "com.codzuregroup.daycall.ui.alarm.EditAlarmScreen (EditAlarmScreen.kt:76)"
    INVOKESTATIC androidx/compose/runtime/ComposerKt.traceEventStart (IIILjava/lang/String;)V
   L20
    ALOAD 6
    LDC -1757875654
    INVOKEINTERFACE androidx/compose/runtime/Composer.startReplaceGroup (I)V (itf)
    ALOAD 6
    LDC "CC(remember):EditAlarmScreen.kt#9igjgp"
    INVOKESTATIC androidx/compose/runtime/ComposerKt.sourceInformation (Landroidx/compose/runtime/Composer;Ljava/lang/String;)V
    ALOAD 6
    ASTORE 11
    NOP
    ICONST_0
    ISTORE 12
   L21
    LINENUMBER 78 L21
    NOP
   L22
    ICONST_0
    ISTORE 13
   L23
    LINENUMBER 568 L23
    ALOAD 11
    INVOKEINTERFACE androidx/compose/runtime/Composer.rememberedValue ()Ljava/lang/Object; (itf)
    ASTORE 14
   L24
    ICONST_0
    ISTORE 15
   L25
    LINENUMBER 569 L25
    ILOAD 12
    IFNE L26
    ALOAD 14
    GETSTATIC androidx/compose/runtime/Composer.Companion : Landroidx/compose/runtime/Composer$Companion;
    INVOKEVIRTUAL androidx/compose/runtime/Composer$Companion.getEmpty ()Ljava/lang/Object;
    IF_ACMPNE L27
   L26
    LINENUMBER 570 L26
    NOP
   L28
    ICONST_0
    ISTORE 16
   L29
    LINENUMBER 78 L29
    ICONST_0
    INVOKESTATIC java/lang/Boolean.valueOf (Z)Ljava/lang/Boolean;
    ACONST_NULL
    ICONST_2
    ACONST_NULL
    INVOKESTATIC androidx/compose/runtime/SnapshotStateKt.mutableStateOf$default (Ljava/lang/Object;Landroidx/compose/runtime/SnapshotMutationPolicy;ILjava/lang/Object;)Landroidx/compose/runtime/MutableState;
    NOP
    GOTO L30
   L30
   L31
    LINENUMBER 570 L31
    ASTORE 16
   L32
    LINENUMBER 571 L32
    ALOAD 11
    ALOAD 16
    INVOKEINTERFACE androidx/compose/runtime/Composer.updateRememberedValue (Ljava/lang/Object;)V (itf)
   L33
    LINENUMBER 572 L33
    ALOAD 16
   L34
    GOTO L35
   L27
    LINENUMBER 573 L27
    ALOAD 14
   L35
    LINENUMBER 569 L35
    NOP
   L36
    LINENUMBER 568 L36
    NOP
   L37
    LINENUMBER 568 L37
    NOP
    GOTO L38
   L38
    LINENUMBER 78 L38
    CHECKCAST androidx/compose/runtime/MutableState
    ASTORE 10
   L39
    ALOAD 6
    INVOKEINTERFACE androidx/compose/runtime/Composer.endReplaceGroup ()V (itf)
    ALOAD 10
   L40
    ASTORE 9
   L41
    ALOAD 6
    LDC -1757873638
    INVOKEINTERFACE androidx/compose/runtime/Composer.startReplaceGroup (I)V (itf)
    ALOAD 6
    LDC "CC(remember):EditAlarmScreen.kt#9igjgp"
    INVOKESTATIC androidx/compose/runtime/ComposerKt.sourceInformation (Landroidx/compose/runtime/Composer;Ljava/lang/String;)V
    ALOAD 6
    ASTORE 12
    NOP
    ICONST_0
    ISTORE 13
   L42
    LINENUMBER 79 L42
    NOP
   L43
    ICONST_0
    ISTORE 14
   L44
    LINENUMBER 574 L44
    ALOAD 12
    INVOKEINTERFACE androidx/compose/runtime/Composer.rememberedValue ()Ljava/lang/Object; (itf)
    ASTORE 15
   L45
    ICONST_0
    ISTORE 16
   L46
    LINENUMBER 575 L46
    ILOAD 13
    IFNE L47
    ALOAD 15
    GETSTATIC androidx/compose/runtime/Composer.Companion : Landroidx/compose/runtime/Composer$Companion;
    INVOKEVIRTUAL androidx/compose/runtime/Composer$Companion.getEmpty ()Ljava/lang/Object;
    IF_ACMPNE L48
   L47
    LINENUMBER 576 L47
    NOP
   L49
    ICONST_0
    ISTORE 17
   L50
    LINENUMBER 79 L50
    ICONST_0
    INVOKESTATIC java/lang/Boolean.valueOf (Z)Ljava/lang/Boolean;
    ACONST_NULL
    ICONST_2
    ACONST_NULL
    INVOKESTATIC androidx/compose/runtime/SnapshotStateKt.mutableStateOf$default (Ljava/lang/Object;Landroidx/compose/runtime/SnapshotMutationPolicy;ILjava/lang/Object;)Landroidx/compose/runtime/MutableState;
    NOP
    GOTO L51
   L51
   L52
    LINENUMBER 576 L52
    ASTORE 17
   L53
    LINENUMBER 577 L53
    ALOAD 12
    ALOAD 17
    INVOKEINTERFACE androidx/compose/runtime/Composer.updateRememberedValue (Ljava/lang/Object;)V (itf)
   L54
    LINENUMBER 578 L54
    ALOAD 17
   L55
    GOTO L56
   L48
    LINENUMBER 579 L48
    ALOAD 15
   L56
    LINENUMBER 575 L56
    NOP
   L57
    LINENUMBER 574 L57
    NOP
   L58
    LINENUMBER 574 L58
    NOP
    GOTO L59
   L59
    LINENUMBER 79 L59
    CHECKCAST androidx/compose/runtime/MutableState
    ASTORE 11
   L60
    ALOAD 6
    INVOKEINTERFACE androidx/compose/runtime/Composer.endReplaceGroup ()V (itf)
    ALOAD 11
   L61
    ASTORE 10
   L62
    ALOAD 6
    LDC -1757871754
    INVOKEINTERFACE androidx/compose/runtime/Composer.startReplaceGroup (I)V (itf)
    ALOAD 6
    LDC "CC(remember):EditAlarmScreen.kt#9igjgp"
    INVOKESTATIC androidx/compose/runtime/ComposerKt.sourceInformation (Landroidx/compose/runtime/Composer;Ljava/lang/String;)V
    ALOAD 6
    ASTORE 13
    NOP
    ICONST_0
    ISTORE 14
   L63
    LINENUMBER 80 L63
    NOP
   L64
    ICONST_0
    ISTORE 15
   L65
    LINENUMBER 580 L65
    ALOAD 13
    INVOKEINTERFACE androidx/compose/runtime/Composer.rememberedValue ()Ljava/lang/Object; (itf)
    ASTORE 16
   L66
    ICONST_0
    ISTORE 17
   L67
    LINENUMBER 581 L67
    ILOAD 14
    IFNE L68
    ALOAD 16
    GETSTATIC androidx/compose/runtime/Composer.Companion : Landroidx/compose/runtime/Composer$Companion;
    INVOKEVIRTUAL androidx/compose/runtime/Composer$Companion.getEmpty ()Ljava/lang/Object;
    IF_ACMPNE L69
   L68
    LINENUMBER 582 L68
    NOP
   L70
    ICONST_0
    ISTORE 18
   L71
    LINENUMBER 80 L71
    BIPUSH 8
    INVOKESTATIC java/lang/Integer.valueOf (I)Ljava/lang/Integer;
    ACONST_NULL
    ICONST_2
    ACONST_NULL
    INVOKESTATIC androidx/compose/runtime/SnapshotStateKt.mutableStateOf$default (Ljava/lang/Object;Landroidx/compose/runtime/SnapshotMutationPolicy;ILjava/lang/Object;)Landroidx/compose/runtime/MutableState;
    NOP
    GOTO L72
   L72
   L73
    LINENUMBER 582 L73
    ASTORE 18
   L74
    LINENUMBER 583 L74
    ALOAD 13
    ALOAD 18
    INVOKEINTERFACE androidx/compose/runtime/Composer.updateRememberedValue (Ljava/lang/Object;)V (itf)
   L75
    LINENUMBER 584 L75
    ALOAD 18
   L76
    GOTO L77
   L69
    LINENUMBER 585 L69
    ALOAD 16
   L77
    LINENUMBER 581 L77
    NOP
   L78
    LINENUMBER 580 L78
    NOP
   L79
    LINENUMBER 580 L79
    NOP
    GOTO L80
   L80
    LINENUMBER 80 L80
    CHECKCAST androidx/compose/runtime/MutableState
    ASTORE 12
   L81
    ALOAD 6
    INVOKEINTERFACE androidx/compose/runtime/Composer.endReplaceGroup ()V (itf)
    ALOAD 12
   L82
    ASTORE 11
   L83
    ALOAD 6
    LDC -1757869930
    INVOKEINTERFACE androidx/compose/runtime/Composer.startReplaceGroup (I)V (itf)
    ALOAD 6
    LDC "CC(remember):EditAlarmScreen.kt#9igjgp"
    INVOKESTATIC androidx/compose/runtime/ComposerKt.sourceInformation (Landroidx/compose/runtime/Composer;Ljava/lang/String;)V
    ALOAD 6
    ASTORE 14
    NOP
    ICONST_0
    ISTORE 15
   L84
    LINENUMBER 81 L84
    NOP
   L85
    ICONST_0
    ISTORE 16
   L86
    LINENUMBER 586 L86
    ALOAD 14
    INVOKEINTERFACE androidx/compose/runtime/Composer.rememberedValue ()Ljava/lang/Object; (itf)
    ASTORE 17
   L87
    ICONST_0
    ISTORE 18
   L88
    LINENUMBER 587 L88
    ILOAD 15
    IFNE L89
    ALOAD 17
    GETSTATIC androidx/compose/runtime/Composer.Companion : Landroidx/compose/runtime/Composer$Companion;
    INVOKEVIRTUAL androidx/compose/runtime/Composer$Companion.getEmpty ()Ljava/lang/Object;
    IF_ACMPNE L90
   L89
    LINENUMBER 588 L89
    NOP
   L91
    ICONST_0
    ISTORE 19
   L92
    LINENUMBER 81 L92
    ICONST_0
    INVOKESTATIC java/lang/Integer.valueOf (I)Ljava/lang/Integer;
    ACONST_NULL
    ICONST_2
    ACONST_NULL
    INVOKESTATIC androidx/compose/runtime/SnapshotStateKt.mutableStateOf$default (Ljava/lang/Object;Landroidx/compose/runtime/SnapshotMutationPolicy;ILjava/lang/Object;)Landroidx/compose/runtime/MutableState;
    NOP
    GOTO L93
   L93
   L94
    LINENUMBER 588 L94
    ASTORE 19
   L95
    LINENUMBER 589 L95
    ALOAD 14
    ALOAD 19
    INVOKEINTERFACE androidx/compose/runtime/Composer.updateRememberedValue (Ljava/lang/Object;)V (itf)
   L96
    LINENUMBER 590 L96
    ALOAD 19
   L97
    GOTO L98
   L90
    LINENUMBER 591 L90
    ALOAD 17
   L98
    LINENUMBER 587 L98
    NOP
   L99
    LINENUMBER 586 L99
    NOP
   L100
    LINENUMBER 586 L100
    NOP
    GOTO L101
   L101
    LINENUMBER 81 L101
    CHECKCAST androidx/compose/runtime/MutableState
    ASTORE 13
   L102
    ALOAD 6
    INVOKEINTERFACE androidx/compose/runtime/Composer.endReplaceGroup ()V (itf)
    ALOAD 13
   L103
    ASTORE 12
   L104
    ALOAD 6
    LDC -1757868233
    INVOKEINTERFACE androidx/compose/runtime/Composer.startReplaceGroup (I)V (itf)
    ALOAD 6
    LDC "CC(remember):EditAlarmScreen.kt#9igjgp"
    INVOKESTATIC androidx/compose/runtime/ComposerKt.sourceInformation (Landroidx/compose/runtime/Composer;Ljava/lang/String;)V
    ALOAD 6
    ASTORE 15
    NOP
    ICONST_0
    ISTORE 16
   L105
    LINENUMBER 82 L105
    NOP
   L106
    ICONST_0
    ISTORE 17
   L107
    LINENUMBER 592 L107
    ALOAD 15
    INVOKEINTERFACE androidx/compose/runtime/Composer.rememberedValue ()Ljava/lang/Object; (itf)
    ASTORE 18
   L108
    ICONST_0
    ISTORE 19
   L109
    LINENUMBER 593 L109
    ILOAD 16
    IFNE L110
    ALOAD 18
    GETSTATIC androidx/compose/runtime/Composer.Companion : Landroidx/compose/runtime/Composer$Companion;
    INVOKEVIRTUAL androidx/compose/runtime/Composer$Companion.getEmpty ()Ljava/lang/Object;
    IF_ACMPNE L111
   L110
    LINENUMBER 594 L110
    NOP
   L112
    ICONST_0
    ISTORE 20
   L113
    LINENUMBER 82 L113
    LDC ""
    ACONST_NULL
    ICONST_2
    ACONST_NULL
    INVOKESTATIC androidx/compose/runtime/SnapshotStateKt.mutableStateOf$default (Ljava/lang/Object;Landroidx/compose/runtime/SnapshotMutationPolicy;ILjava/lang/Object;)Landroidx/compose/runtime/MutableState;
    NOP
    GOTO L114
   L114
   L115
    LINENUMBER 594 L115
    ASTORE 20
   L116
    LINENUMBER 595 L116
    ALOAD 15
    ALOAD 20
    INVOKEINTERFACE androidx/compose/runtime/Composer.updateRememberedValue (Ljava/lang/Object;)V (itf)
   L117
    LINENUMBER 596 L117
    ALOAD 20
   L118
    GOTO L119
   L111
    LINENUMBER 597 L111
    ALOAD 18
   L119
    LINENUMBER 593 L119
    NOP
   L120
    LINENUMBER 592 L120
    NOP
   L121
    LINENUMBER 592 L121
    NOP
    GOTO L122
   L122
    LINENUMBER 82 L122
    CHECKCAST androidx/compose/runtime/MutableState
    ASTORE 14
   L123
    ALOAD 6
    INVOKEINTERFACE androidx/compose/runtime/Composer.endReplaceGroup ()V (itf)
    ALOAD 14
   L124
    ASTORE 13
   L125
    ALOAD 6
    LDC -1757866396
    INVOKEINTERFACE androidx/compose/runtime/Composer.startReplaceGroup (I)V (itf)
    ALOAD 6
    LDC "CC(remember):EditAlarmScreen.kt#9igjgp"
    INVOKESTATIC androidx/compose/runtime/ComposerKt.sourceInformation (Landroidx/compose/runtime/Composer;Ljava/lang/String;)V
    ALOAD 6
    ASTORE 16
    NOP
    ICONST_0
    ISTORE 17
   L126
    LINENUMBER 83 L126
    NOP
   L127
    ICONST_0
    ISTORE 18
   L128
    LINENUMBER 598 L128
    ALOAD 16
    INVOKEINTERFACE androidx/compose/runtime/Composer.rememberedValue ()Ljava/lang/Object; (itf)
    ASTORE 19
   L129
    ICONST_0
    ISTORE 20
   L130
    LINENUMBER 599 L130
    ILOAD 17
    IFNE L131
    ALOAD 19
    GETSTATIC androidx/compose/runtime/Composer.Companion : Landroidx/compose/runtime/Composer$Companion;
    INVOKEVIRTUAL androidx/compose/runtime/Composer$Companion.getEmpty ()Ljava/lang/Object;
    IF_ACMPNE L132
   L131
    LINENUMBER 600 L131
    NOP
   L133
    ICONST_0
    ISTORE 21
   L134
    LINENUMBER 83 L134
    LDC "default_alarm"
    ACONST_NULL
    ICONST_2
    ACONST_NULL
    INVOKESTATIC androidx/compose/runtime/SnapshotStateKt.mutableStateOf$default (Ljava/lang/Object;Landroidx/compose/runtime/SnapshotMutationPolicy;ILjava/lang/Object;)Landroidx/compose/runtime/MutableState;
    NOP
    GOTO L135
   L135
   L136
    LINENUMBER 600 L136
    ASTORE 21
   L137
    LINENUMBER 601 L137
    ALOAD 16
    ALOAD 21
    INVOKEINTERFACE androidx/compose/runtime/Composer.updateRememberedValue (Ljava/lang/Object;)V (itf)
   L138
    LINENUMBER 602 L138
    ALOAD 21
   L139
    GOTO L140
   L132
    LINENUMBER 603 L132
    ALOAD 19
   L140
    LINENUMBER 599 L140
    NOP
   L141
    LINENUMBER 598 L141
    NOP
   L142
    LINENUMBER 598 L142
    NOP
    GOTO L143
   L143
    LINENUMBER 83 L143
    CHECKCAST androidx/compose/runtime/MutableState
    ASTORE 15
   L144
    ALOAD 6
    INVOKEINTERFACE androidx/compose/runtime/Composer.endReplaceGroup ()V (itf)
    ALOAD 15
   L145
    ASTORE 14
   L146
    ALOAD 6
    LDC -1757864196
    INVOKEINTERFACE androidx/compose/runtime/Composer.startReplaceGroup (I)V (itf)
    ALOAD 6
    LDC "CC(remember):EditAlarmScreen.kt#9igjgp"
    INVOKESTATIC androidx/compose/runtime/ComposerKt.sourceInformation (Landroidx/compose/runtime/Composer;Ljava/lang/String;)V
    ALOAD 6
    ASTORE 17
    NOP
    ICONST_0
    ISTORE 18
   L147
    LINENUMBER 84 L147
    NOP
   L148
    ICONST_0
    ISTORE 19
   L149
    LINENUMBER 604 L149
    ALOAD 17
    INVOKEINTERFACE androidx/compose/runtime/Composer.rememberedValue ()Ljava/lang/Object; (itf)
    ASTORE 20
   L150
    ICONST_0
    ISTORE 21
   L151
    LINENUMBER 605 L151
    ILOAD 18
    IFNE L152
    ALOAD 20
    GETSTATIC androidx/compose/runtime/Composer.Companion : Landroidx/compose/runtime/Composer$Companion;
    INVOKEVIRTUAL androidx/compose/runtime/Composer$Companion.getEmpty ()Ljava/lang/Object;
    IF_ACMPNE L153
   L152
    LINENUMBER 606 L152
    NOP
   L154
    ICONST_0
    ISTORE 22
   L155
    LINENUMBER 84 L155
    LDC "chill"
    ACONST_NULL
    ICONST_2
    ACONST_NULL
    INVOKESTATIC androidx/compose/runtime/SnapshotStateKt.mutableStateOf$default (Ljava/lang/Object;Landroidx/compose/runtime/SnapshotMutationPolicy;ILjava/lang/Object;)Landroidx/compose/runtime/MutableState;
    NOP
    GOTO L156
   L156
   L157
    LINENUMBER 606 L157
    ASTORE 22
   L158
    LINENUMBER 607 L158
    ALOAD 17
    ALOAD 22
    INVOKEINTERFACE androidx/compose/runtime/Composer.updateRememberedValue (Ljava/lang/Object;)V (itf)
   L159
    LINENUMBER 608 L159
    ALOAD 22
   L160
    GOTO L161
   L153
    LINENUMBER 609 L153
    ALOAD 20
   L161
    LINENUMBER 605 L161
    NOP
   L162
    LINENUMBER 604 L162
    NOP
   L163
    LINENUMBER 604 L163
    NOP
    GOTO L164
   L164
    LINENUMBER 84 L164
    CHECKCAST androidx/compose/runtime/MutableState
    ASTORE 16
   L165
    ALOAD 6
    INVOKEINTERFACE androidx/compose/runtime/Composer.endReplaceGroup ()V (itf)
    ALOAD 16
   L166
    ASTORE 15
   L167
    ALOAD 6
    LDC -1757862343
    INVOKEINTERFACE androidx/compose/runtime/Composer.startReplaceGroup (I)V (itf)
    ALOAD 6
    LDC "CC(remember):EditAlarmScreen.kt#9igjgp"
    INVOKESTATIC androidx/compose/runtime/ComposerKt.sourceInformation (Landroidx/compose/runtime/Composer;Ljava/lang/String;)V
    ALOAD 6
    ASTORE 18
    NOP
    ICONST_0
    ISTORE 19
   L168
    LINENUMBER 85 L168
    NOP
   L169
    ICONST_0
    ISTORE 20
   L170
    LINENUMBER 610 L170
    ALOAD 18
    INVOKEINTERFACE androidx/compose/runtime/Composer.rememberedValue ()Ljava/lang/Object; (itf)
    ASTORE 21
   L171
    ICONST_0
    ISTORE 22
   L172
    LINENUMBER 611 L172
    ILOAD 19
    IFNE L173
    ALOAD 21
    GETSTATIC androidx/compose/runtime/Composer.Companion : Landroidx/compose/runtime/Composer$Companion;
    INVOKEVIRTUAL androidx/compose/runtime/Composer$Companion.getEmpty ()Ljava/lang/Object;
    IF_ACMPNE L174
   L173
    LINENUMBER 612 L173
    NOP
   L175
    ICONST_0
    ISTORE 23
   L176
    LINENUMBER 85 L176
    ICONST_1
    INVOKESTATIC java/lang/Boolean.valueOf (Z)Ljava/lang/Boolean;
    ACONST_NULL
    ICONST_2
    ACONST_NULL
    INVOKESTATIC androidx/compose/runtime/SnapshotStateKt.mutableStateOf$default (Ljava/lang/Object;Landroidx/compose/runtime/SnapshotMutationPolicy;ILjava/lang/Object;)Landroidx/compose/runtime/MutableState;
    NOP
    GOTO L177
   L177
   L178
    LINENUMBER 612 L178
    ASTORE 23
   L179
    LINENUMBER 613 L179
    ALOAD 18
    ALOAD 23
    INVOKEINTERFACE androidx/compose/runtime/Composer.updateRememberedValue (Ljava/lang/Object;)V (itf)
   L180
    LINENUMBER 614 L180
    ALOAD 23
   L181
    GOTO L182
   L174
    LINENUMBER 615 L174
    ALOAD 21
   L182
    LINENUMBER 611 L182
    NOP
   L183
    LINENUMBER 610 L183
    NOP
   L184
    LINENUMBER 610 L184
    NOP
    GOTO L185
   L185
    LINENUMBER 85 L185
    CHECKCAST androidx/compose/runtime/MutableState
    ASTORE 17
   L186
    ALOAD 6
    INVOKEINTERFACE androidx/compose/runtime/Composer.endReplaceGroup ()V (itf)
    ALOAD 17
   L187
    ASTORE 16
   L188
    ALOAD 6
    LDC -1757860473
    INVOKEINTERFACE androidx/compose/runtime/Composer.startReplaceGroup (I)V (itf)
    ALOAD 6
    LDC "CC(remember):EditAlarmScreen.kt#9igjgp"
    INVOKESTATIC androidx/compose/runtime/ComposerKt.sourceInformation (Landroidx/compose/runtime/Composer;Ljava/lang/String;)V
    ALOAD 6
    ASTORE 19
    NOP
    ICONST_0
    ISTORE 20
   L189
    LINENUMBER 86 L189
    NOP
   L190
    ICONST_0
    ISTORE 21
   L191
    LINENUMBER 616 L191
    ALOAD 19
    INVOKEINTERFACE androidx/compose/runtime/Composer.rememberedValue ()Ljava/lang/Object; (itf)
    ASTORE 22
   L192
    ICONST_0
    ISTORE 23
   L193
    LINENUMBER 617 L193
    ILOAD 20
    IFNE L194
    ALOAD 22
    GETSTATIC androidx/compose/runtime/Composer.Companion : Landroidx/compose/runtime/Composer$Companion;
    INVOKEVIRTUAL androidx/compose/runtime/Composer$Companion.getEmpty ()Ljava/lang/Object;
    IF_ACMPNE L195
   L194
    LINENUMBER 618 L194
    NOP
   L196
    ICONST_0
    ISTORE 24
   L197
    LINENUMBER 86 L197
    ACONST_NULL
    ACONST_NULL
    ICONST_2
    ACONST_NULL
    INVOKESTATIC androidx/compose/runtime/SnapshotStateKt.mutableStateOf$default (Ljava/lang/Object;Landroidx/compose/runtime/SnapshotMutationPolicy;ILjava/lang/Object;)Landroidx/compose/runtime/MutableState;
    NOP
    GOTO L198
   L198
   L199
    LINENUMBER 618 L199
    ASTORE 24
   L200
    LINENUMBER 619 L200
    ALOAD 19
    ALOAD 24
    INVOKEINTERFACE androidx/compose/runtime/Composer.updateRememberedValue (Ljava/lang/Object;)V (itf)
   L201
    LINENUMBER 620 L201
    ALOAD 24
   L202
    GOTO L203
   L195
    LINENUMBER 621 L195
    ALOAD 22
   L203
    LINENUMBER 617 L203
    NOP
   L204
    LINENUMBER 616 L204
    NOP
   L205
    LINENUMBER 616 L205
    NOP
    GOTO L206
   L206
    LINENUMBER 86 L206
    CHECKCAST androidx/compose/runtime/MutableState
    ASTORE 18
   L207
    ALOAD 6
    INVOKEINTERFACE androidx/compose/runtime/Composer.endReplaceGroup ()V (itf)
    ALOAD 18
   L208
    ASTORE 17
   L209
    LINENUMBER 88 L209
    INVOKESTATIC androidx/compose/ui/platform/AndroidCompositionLocals_androidKt.getLocalContext ()Landroidx/compose/runtime/ProvidableCompositionLocal;
    CHECKCAST androidx/compose/runtime/CompositionLocal
    ASTORE 19
    ICONST_0
    ISTORE 20
    NOP
   L210
    ICONST_0
    ISTORE 21
   L211
    ALOAD 6
    LDC 2023513938
    LDC "CC:CompositionLocal.kt#9igjgp"
   L212
    LINENUMBER 622 L212
    INVOKESTATIC androidx/compose/runtime/ComposerKt.sourceInformationMarkerStart (Landroidx/compose/runtime/Composer;ILjava/lang/String;)V
    ALOAD 6
    ALOAD 19
    INVOKEINTERFACE androidx/compose/runtime/Composer.consume (Landroidx/compose/runtime/CompositionLocal;)Ljava/lang/Object; (itf)
    ASTORE 22
    ALOAD 6
    INVOKESTATIC androidx/compose/runtime/ComposerKt.sourceInformationMarkerEnd (Landroidx/compose/runtime/Composer;)V
    ALOAD 22
    NOP
    GOTO L213
   L213
    LINENUMBER 88 L213
    CHECKCAST android/content/Context
    ASTORE 18
   L214
    ALOAD 6
    LDC -1757856695
    INVOKEINTERFACE androidx/compose/runtime/Composer.startReplaceGroup (I)V (itf)
    ALOAD 6
    LDC "CC(remember):EditAlarmScreen.kt#9igjgp"
    INVOKESTATIC androidx/compose/runtime/ComposerKt.sourceInformation (Landroidx/compose/runtime/Composer;Ljava/lang/String;)V
    ALOAD 6
    ASTORE 21
    NOP
    ICONST_0
    ISTORE 22
   L215
    LINENUMBER 89 L215
    NOP
   L216
    ICONST_0
    ISTORE 23
   L217
    LINENUMBER 623 L217
    ALOAD 21
    INVOKEINTERFACE androidx/compose/runtime/Composer.rememberedValue ()Ljava/lang/Object; (itf)
    ASTORE 24
   L218
    ICONST_0
    ISTORE 25
   L219
    LINENUMBER 624 L219
    ILOAD 22
    IFNE L220
    ALOAD 24
    GETSTATIC androidx/compose/runtime/Composer.Companion : Landroidx/compose/runtime/Composer$Companion;
    INVOKEVIRTUAL androidx/compose/runtime/Composer$Companion.getEmpty ()Ljava/lang/Object;
    IF_ACMPNE L221
   L220
    LINENUMBER 625 L220
    NOP
   L222
    ICONST_0
    ISTORE 26
   L223
    LINENUMBER 89 L223
    GETSTATIC com/codzuregroup/daycall/ui/settings/SettingsManager.Companion : Lcom/codzuregroup/daycall/ui/settings/SettingsManager$Companion;
    ALOAD 18
    INVOKEVIRTUAL com/codzuregroup/daycall/ui/settings/SettingsManager$Companion.getInstance (Landroid/content/Context;)Lcom/codzuregroup/daycall/ui/settings/SettingsManager;
    NOP
    GOTO L224
   L224
   L225
    LINENUMBER 625 L225
    ASTORE 27
   L226
    LINENUMBER 626 L226
    ALOAD 21
    ALOAD 27
    INVOKEINTERFACE androidx/compose/runtime/Composer.updateRememberedValue (Ljava/lang/Object;)V (itf)
   L227
    LINENUMBER 627 L227
    ALOAD 27
   L228
    GOTO L229
   L221
    LINENUMBER 628 L221
    ALOAD 24
   L229
    LINENUMBER 624 L229
    NOP
   L230
    LINENUMBER 623 L230
    NOP
   L231
    LINENUMBER 623 L231
    NOP
    GOTO L232
   L232
    LINENUMBER 89 L232
    CHECKCAST com/codzuregroup/daycall/ui/settings/SettingsManager
    ASTORE 20
   L233
    ALOAD 6
    INVOKEINTERFACE androidx/compose/runtime/Composer.endReplaceGroup ()V (itf)
    ALOAD 20
   L234
    ASTORE 19
   L235
    LINENUMBER 90 L235
    ALOAD 19
    INVOKEVIRTUAL com/codzuregroup/daycall/ui/settings/SettingsManager.getTimeFormat ()Lkotlinx/coroutines/flow/StateFlow;
    ACONST_NULL
    ACONST_NULL
    ACONST_NULL
    ALOAD 6
    ICONST_0
    BIPUSH 7
    INVOKESTATIC androidx/lifecycle/compose/FlowExtKt.collectAsStateWithLifecycle (Lkotlinx/coroutines/flow/StateFlow;Landroidx/lifecycle/LifecycleOwner;Landroidx/lifecycle/Lifecycle$State;Lkotlin/coroutines/CoroutineContext;Landroidx/compose/runtime/Composer;II)Landroidx/compose/runtime/State;
    ASTORE 20
   L236
    LINENUMBER 92 L236
    ALOAD 20
    INVOKESTATIC com/codzuregroup/daycall/ui/alarm/EditAlarmScreenKt.EditAlarmScreen$lambda$28 (Landroidx/compose/runtime/State;)Lcom/codzuregroup/daycall/ui/settings/TimeFormat;
    ASTORE 22
   L237
    GETSTATIC com/codzuregroup/daycall/ui/alarm/EditAlarmScreenKt$WhenMappings.$EnumSwitchMapping$0 : [I
    ALOAD 22
    INVOKEVIRTUAL com/codzuregroup/daycall/ui/settings/TimeFormat.ordinal ()I
    IALOAD
    ISTORE 23
   L238
    ILOAD 23
    TABLESWITCH
      1: L239
      2: L240
      default: L241
   L239
    LINENUMBER 93 L239
    LDC "hh:mm"
    INVOKESTATIC java/time/format/DateTimeFormatter.ofPattern (Ljava/lang/String;)Ljava/time/format/DateTimeFormatter;
    GOTO L242
   L240
    LINENUMBER 94 L240
    LDC "HH:mm"
    INVOKESTATIC java/time/format/DateTimeFormatter.ofPattern (Ljava/lang/String;)Ljava/time/format/DateTimeFormatter;
    GOTO L242
   L241
    LINENUMBER 95 L241
    LDC "hh:mm"
    INVOKESTATIC java/time/format/DateTimeFormatter.ofPattern (Ljava/lang/String;)Ljava/time/format/DateTimeFormatter;
   L242
    LINENUMBER 92 L242
    ASTORE 21
   L243
    LINENUMBER 97 L243
    LDC "a"
    INVOKESTATIC java/time/format/DateTimeFormatter.ofPattern (Ljava/lang/String;)Ljava/time/format/DateTimeFormatter;
    ASTORE 22
   L244
    LINENUMBER 98 L244
    ALOAD 11
    INVOKESTATIC com/codzuregroup/daycall/ui/alarm/EditAlarmScreenKt.EditAlarmScreen$lambda$7 (Landroidx/compose/runtime/MutableState;)I
    ALOAD 12
    INVOKESTATIC com/codzuregroup/daycall/ui/alarm/EditAlarmScreenKt.EditAlarmScreen$lambda$10 (Landroidx/compose/runtime/MutableState;)I
    INVOKESTATIC java/time/LocalTime.of (II)Ljava/time/LocalTime;
    ASTORE 23
   L245
    LINENUMBER 101 L245
    LLOAD 0
    INVOKESTATIC java/lang/Long.valueOf (J)Ljava/lang/Long;
    ALOAD 6
    LDC -1757838838
    INVOKEINTERFACE androidx/compose/runtime/Composer.startReplaceGroup (I)V (itf)
    ALOAD 6
    LDC "CC(remember):EditAlarmScreen.kt#9igjgp"
    INVOKESTATIC androidx/compose/runtime/ComposerKt.sourceInformation (Landroidx/compose/runtime/Composer;Ljava/lang/String;)V
    ALOAD 6
    ASTORE 25
    ALOAD 6
    ALOAD 2
    INVOKEINTERFACE androidx/compose/runtime/Composer.changedInstance (Ljava/lang/Object;)Z (itf)
    ILOAD 8
    BIPUSH 14
    IAND
    ICONST_4
    IF_ICMPNE L246
    ICONST_1
    GOTO L247
   L246
    ICONST_0
   L247
    IOR
    ISTORE 26
    NOP
   L248
    ICONST_0
    ISTORE 27
   L249
    LINENUMBER 629 L249
    ALOAD 25
    INVOKEINTERFACE androidx/compose/runtime/Composer.rememberedValue ()Ljava/lang/Object; (itf)
    ASTORE 28
   L250
    ICONST_0
    ISTORE 29
   L251
    LINENUMBER 630 L251
    ILOAD 26
    IFNE L252
    ALOAD 28
    GETSTATIC androidx/compose/runtime/Composer.Companion : Landroidx/compose/runtime/Composer$Companion;
    INVOKEVIRTUAL androidx/compose/runtime/Composer$Companion.getEmpty ()Ljava/lang/Object;
    IF_ACMPNE L253
   L252
    LINENUMBER 631 L252
    NOP
    ASTORE 32
   L254
    ICONST_0
    ISTORE 30
   L255
    LINENUMBER 101 L255
    NEW com/codzuregroup/daycall/ui/alarm/EditAlarmScreenKt$EditAlarmScreen$1$1
    DUP
    ALOAD 2
    LLOAD 0
    ALOAD 17
    ALOAD 11
    ALOAD 12
    ALOAD 13
    ALOAD 14
    ALOAD 15
    ALOAD 16
    ACONST_NULL
    INVOKESPECIAL com/codzuregroup/daycall/ui/alarm/EditAlarmScreenKt$EditAlarmScreen$1$1.<init> (Lcom/codzuregroup/daycall/ui/AlarmViewModel;JLandroidx/compose/runtime/MutableState;Landroidx/compose/runtime/MutableState;Landroidx/compose/runtime/MutableState;Landroidx/compose/runtime/MutableState;Landroidx/compose/runtime/MutableState;Landroidx/compose/runtime/MutableState;Landroidx/compose/runtime/MutableState;Lkotlin/coroutines/Continuation;)V
    CHECKCAST kotlin/jvm/functions/Function2
    NOP
    GOTO L256
   L256
    ASTORE 33
    ALOAD 32
    ALOAD 33
   L257
    LINENUMBER 631 L257
    ASTORE 31
   L258
    LINENUMBER 632 L258
    ALOAD 25
    ALOAD 31
    INVOKEINTERFACE androidx/compose/runtime/Composer.updateRememberedValue (Ljava/lang/Object;)V (itf)
   L259
    LINENUMBER 633 L259
    ALOAD 31
   L260
    GOTO L261
   L253
    LINENUMBER 634 L253
    ALOAD 28
   L261
    LINENUMBER 630 L261
    NOP
   L262
    LINENUMBER 629 L262
    NOP
   L263
    LINENUMBER 629 L263
    NOP
    GOTO L264
   L264
    LINENUMBER 101 L264
    CHECKCAST kotlin/jvm/functions/Function2
    ASTORE 24
   L265
    ALOAD 6
    INVOKEINTERFACE androidx/compose/runtime/Composer.endReplaceGroup ()V (itf)
    ALOAD 24
   L266
    ALOAD 6
    BIPUSH 14
    ILOAD 8
    IAND
    INVOKESTATIC androidx/compose/runtime/EffectsKt.LaunchedEffect (Ljava/lang/Object;Lkotlin/jvm/functions/Function2;Landroidx/compose/runtime/Composer;I)V
   L267
    LINENUMBER 115 L267
    GETSTATIC androidx/compose/ui/Modifier.Companion : Landroidx/compose/ui/Modifier$Companion;
    CHECKCAST androidx/compose/ui/Modifier
    FCONST_0
    ICONST_1
    ACONST_NULL
    INVOKESTATIC androidx/compose/foundation/layout/SizeKt.fillMaxSize$default (Landroidx/compose/ui/Modifier;FILjava/lang/Object;)Landroidx/compose/ui/Modifier;
    ASTORE 24
   L268
    LINENUMBER 116 L268
    GETSTATIC androidx/compose/ui/graphics/Color.Companion : Landroidx/compose/ui/graphics/Color$Companion;
    INVOKEVIRTUAL androidx/compose/ui/graphics/Color$Companion.getWhite-0d7_KjU ()J
    LSTORE 25
   L269
    LINENUMBER 115 L269
    ALOAD 24
   L270
    LINENUMBER 117 L270
    LDC -470567540
    NOP
    ICONST_1
    NEW com/codzuregroup/daycall/ui/alarm/EditAlarmScreenKt$EditAlarmScreen$2
    DUP
    ALOAD 3
    ALOAD 4
    ALOAD 10
    ALOAD 17
    ALOAD 11
    ALOAD 12
    ALOAD 13
    ALOAD 14
    ALOAD 15
    ALOAD 16
    INVOKESPECIAL com/codzuregroup/daycall/ui/alarm/EditAlarmScreenKt$EditAlarmScreen$2.<init> (Lkotlin/jvm/functions/Function0;Lkotlin/jvm/functions/Function1;Landroidx/compose/runtime/MutableState;Landroidx/compose/runtime/MutableState;Landroidx/compose/runtime/MutableState;Landroidx/compose/runtime/MutableState;Landroidx/compose/runtime/MutableState;Landroidx/compose/runtime/MutableState;Landroidx/compose/runtime/MutableState;Landroidx/compose/runtime/MutableState;)V
    ALOAD 6
    BIPUSH 54
    INVOKESTATIC androidx/compose/runtime/internal/ComposableLambdaKt.rememberComposableLambda (IZLjava/lang/Object;Landroidx/compose/runtime/Composer;I)Landroidx/compose/runtime/internal/ComposableLambda;
    CHECKCAST kotlin/jvm/functions/Function2
    ACONST_NULL
    ACONST_NULL
    ACONST_NULL
    ICONST_0
   L271
    LINENUMBER 116 L271
    LLOAD 25
    LCONST_0
    ACONST_NULL
   L272
    LINENUMBER 173 L272
    LDC 883010657
    NOP
    ICONST_1
    NEW com/codzuregroup/daycall/ui/alarm/EditAlarmScreenKt$EditAlarmScreen$3
    DUP
    ALOAD 4
    ALOAD 23
    ALOAD 21
    ALOAD 22
    ALOAD 20
    ALOAD 9
    ALOAD 13
    ALOAD 15
    ALOAD 17
    ALOAD 11
    ALOAD 12
    ALOAD 14
    ALOAD 16
    INVOKESPECIAL com/codzuregroup/daycall/ui/alarm/EditAlarmScreenKt$EditAlarmScreen$3.<init> (Lkotlin/jvm/functions/Function1;Ljava/time/LocalTime;Ljava/time/format/DateTimeFormatter;Ljava/time/format/DateTimeFormatter;Landroidx/compose/runtime/State;Landroidx/compose/runtime/MutableState;Landroidx/compose/runtime/MutableState;Landroidx/compose/runtime/MutableState;Landroidx/compose/runtime/MutableState;Landroidx/compose/runtime/MutableState;Landroidx/compose/runtime/MutableState;Landroidx/compose/runtime/MutableState;Landroidx/compose/runtime/MutableState;)V
    ALOAD 6
    BIPUSH 54
    INVOKESTATIC androidx/compose/runtime/internal/ComposableLambdaKt.rememberComposableLambda (IZLjava/lang/Object;Landroidx/compose/runtime/Composer;I)Landroidx/compose/runtime/internal/ComposableLambda;
    CHECKCAST kotlin/jvm/functions/Function3
    ALOAD 6
    LDC 806879286
    SIPUSH 444
   L273
    LINENUMBER 114 L273
    INVOKESTATIC androidx/compose/material3/ScaffoldKt.Scaffold-TvnljyQ (Landroidx/compose/ui/Modifier;Lkotlin/jvm/functions/Function2;Lkotlin/jvm/functions/Function2;Lkotlin/jvm/functions/Function2;Lkotlin/jvm/functions/Function2;IJJLandroidx/compose/foundation/layout/WindowInsets;Lkotlin/jvm/functions/Function3;Landroidx/compose/runtime/Composer;II)V
   L274
    ALOAD 6
    LDC -1757344116
    INVOKEINTERFACE androidx/compose/runtime/Composer.startReplaceGroup (I)V (itf)
    ALOAD 6
    LDC "466@19979L26,505@21861L213,514@22104L173,468@20071L1760,465@19935L2352"
    INVOKESTATIC androidx/compose/runtime/ComposerKt.sourceInformation (Landroidx/compose/runtime/Composer;Ljava/lang/String;)V
   L275
    LINENUMBER 465 L275
    ALOAD 9
    INVOKESTATIC com/codzuregroup/daycall/ui/alarm/EditAlarmScreenKt.EditAlarmScreen$lambda$1 (Landroidx/compose/runtime/MutableState;)Z
    IFEQ L276
    ALOAD 6
    LDC -1757344110
    INVOKEINTERFACE androidx/compose/runtime/Composer.startReplaceGroup (I)V (itf)
    ALOAD 6
    LDC "CC(remember):EditAlarmScreen.kt#9igjgp"
    INVOKESTATIC androidx/compose/runtime/ComposerKt.sourceInformation (Landroidx/compose/runtime/Composer;Ljava/lang/String;)V
    ALOAD 6
    ASTORE 25
    NOP
    ICONST_0
    ISTORE 26
   L277
    LINENUMBER 467 L277
    NOP
   L278
    ICONST_0
    ISTORE 27
   L279
    LINENUMBER 635 L279
    ALOAD 25
    INVOKEINTERFACE androidx/compose/runtime/Composer.rememberedValue ()Ljava/lang/Object; (itf)
    ASTORE 28
   L280
    ICONST_0
    ISTORE 29
   L281
    LINENUMBER 636 L281
    ILOAD 26
    IFNE L282
    ALOAD 28
    GETSTATIC androidx/compose/runtime/Composer.Companion : Landroidx/compose/runtime/Composer$Companion;
    INVOKEVIRTUAL androidx/compose/runtime/Composer$Companion.getEmpty ()Ljava/lang/Object;
    IF_ACMPNE L283
   L282
    LINENUMBER 637 L282
    NOP
   L284
    ICONST_0
    ISTORE 30
   L285
    LINENUMBER 467 L285
    ALOAD 9
    INVOKEDYNAMIC invoke(Landroidx/compose/runtime/MutableState;)Lkotlin/jvm/functions/Function0; [
      // handle kind 0x6 : INVOKESTATIC
      java/lang/invoke/LambdaMetafactory.metafactory(Ljava/lang/invoke/MethodHandles$Lookup;Ljava/lang/String;Ljava/lang/invoke/MethodType;Ljava/lang/invoke/MethodType;Ljava/lang/invoke/MethodHandle;Ljava/lang/invoke/MethodType;)Ljava/lang/invoke/CallSite;
      // arguments:
      ()Ljava/lang/Object;, 
      // handle kind 0x6 : INVOKESTATIC
      com/codzuregroup/daycall/ui/alarm/EditAlarmScreenKt.EditAlarmScreen$lambda$31$lambda$30(Landroidx/compose/runtime/MutableState;)Lkotlin/Unit;, 
      ()Lkotlin/Unit;
    ]
    NOP
    GOTO L286
   L286
   L287
    LINENUMBER 637 L287
    ASTORE 31
   L288
    LINENUMBER 638 L288
    ALOAD 25
    ALOAD 31
    INVOKEINTERFACE androidx/compose/runtime/Composer.updateRememberedValue (Ljava/lang/Object;)V (itf)
   L289
    LINENUMBER 639 L289
    ALOAD 31
   L290
    GOTO L291
   L283
    LINENUMBER 640 L283
    ALOAD 28
   L291
    LINENUMBER 636 L291
    NOP
   L292
    LINENUMBER 635 L292
    NOP
   L293
    LINENUMBER 635 L293
    NOP
    GOTO L294
   L294
    LINENUMBER 467 L294
    CHECKCAST kotlin/jvm/functions/Function0
    ASTORE 24
   L295
    ALOAD 6
    INVOKEINTERFACE androidx/compose/runtime/Composer.endReplaceGroup ()V (itf)
    ALOAD 24
   L296
    LINENUMBER 506 L296
    LDC 1662643421
    NOP
    ICONST_1
    NEW com/codzuregroup/daycall/ui/alarm/EditAlarmScreenKt$EditAlarmScreen$5
    DUP
    ALOAD 9
    INVOKESPECIAL com/codzuregroup/daycall/ui/alarm/EditAlarmScreenKt$EditAlarmScreen$5.<init> (Landroidx/compose/runtime/MutableState;)V
    ALOAD 6
    BIPUSH 54
    INVOKESTATIC androidx/compose/runtime/internal/ComposableLambdaKt.rememberComposableLambda (IZLjava/lang/Object;Landroidx/compose/runtime/Composer;I)Landroidx/compose/runtime/internal/ComposableLambda;
    CHECKCAST kotlin/jvm/functions/Function2
    ACONST_NULL
   L297
    LINENUMBER 515 L297
    LDC -260607009
    NOP
    ICONST_1
    NEW com/codzuregroup/daycall/ui/alarm/EditAlarmScreenKt$EditAlarmScreen$6
    DUP
    ALOAD 9
    INVOKESPECIAL com/codzuregroup/daycall/ui/alarm/EditAlarmScreenKt$EditAlarmScreen$6.<init> (Landroidx/compose/runtime/MutableState;)V
    ALOAD 6
    BIPUSH 54
    INVOKESTATIC androidx/compose/runtime/internal/ComposableLambdaKt.rememberComposableLambda (IZLjava/lang/Object;Landroidx/compose/runtime/Composer;I)Landroidx/compose/runtime/internal/ComposableLambda;
    CHECKCAST kotlin/jvm/functions/Function2
    ACONST_NULL
    GETSTATIC com/codzuregroup/daycall/ui/alarm/ComposableSingletons$EditAlarmScreenKt.INSTANCE : Lcom/codzuregroup/daycall/ui/alarm/ComposableSingletons$EditAlarmScreenKt;
    INVOKEVIRTUAL com/codzuregroup/daycall/ui/alarm/ComposableSingletons$EditAlarmScreenKt.getLambda-11$app_samsungDebug ()Lkotlin/jvm/functions/Function2;
   L298
    LINENUMBER 469 L298
    LDC 1149484642
    NOP
    ICONST_1
    NEW com/codzuregroup/daycall/ui/alarm/EditAlarmScreenKt$EditAlarmScreen$7
    DUP
    ALOAD 11
    ALOAD 12
    ALOAD 20
    INVOKESPECIAL com/codzuregroup/daycall/ui/alarm/EditAlarmScreenKt$EditAlarmScreen$7.<init> (Landroidx/compose/runtime/MutableState;Landroidx/compose/runtime/MutableState;Landroidx/compose/runtime/State;)V
    ALOAD 6
    BIPUSH 54
    INVOKESTATIC androidx/compose/runtime/internal/ComposableLambdaKt.rememberComposableLambda (IZLjava/lang/Object;Landroidx/compose/runtime/Composer;I)Landroidx/compose/runtime/internal/ComposableLambda;
    CHECKCAST kotlin/jvm/functions/Function2
    ACONST_NULL
    LCONST_0
    LCONST_0
    LCONST_0
    LCONST_0
    FCONST_0
    ACONST_NULL
    ALOAD 6
    LDC 1772598
    ICONST_0
    SIPUSH 16276
   L299
    LINENUMBER 466 L299
    INVOKESTATIC androidx/compose/material3/AndroidAlertDialog_androidKt.AlertDialog-Oix01E0 (Lkotlin/jvm/functions/Function0;Lkotlin/jvm/functions/Function2;Landroidx/compose/ui/Modifier;Lkotlin/jvm/functions/Function2;Lkotlin/jvm/functions/Function2;Lkotlin/jvm/functions/Function2;Lkotlin/jvm/functions/Function2;Landroidx/compose/ui/graphics/Shape;JJJJFLandroidx/compose/ui/window/DialogProperties;Landroidx/compose/runtime/Composer;III)V
   L276
    ALOAD 6
    INVOKEINTERFACE androidx/compose/runtime/Composer.endReplaceGroup ()V (itf)
   L300
    LINENUMBER 526 L300
    ALOAD 10
    INVOKESTATIC com/codzuregroup/daycall/ui/alarm/EditAlarmScreenKt.EditAlarmScreen$lambda$4 (Landroidx/compose/runtime/MutableState;)Z
    IFEQ L301
    ALOAD 6
    LDC -1757265484
    INVOKEINTERFACE androidx/compose/runtime/Composer.startReplaceGroup (I)V (itf)
    ALOAD 6
    LDC "CC(remember):EditAlarmScreen.kt#9igjgp"
    INVOKESTATIC androidx/compose/runtime/ComposerKt.sourceInformation (Landroidx/compose/runtime/Composer;Ljava/lang/String;)V
    ALOAD 6
    ASTORE 25
    NOP
    ICONST_0
    ISTORE 26
   L302
    LINENUMBER 528 L302
    NOP
   L303
    ICONST_0
    ISTORE 27
   L304
    LINENUMBER 641 L304
    ALOAD 25
    INVOKEINTERFACE androidx/compose/runtime/Composer.rememberedValue ()Ljava/lang/Object; (itf)
    ASTORE 28
   L305
    ICONST_0
    ISTORE 29
   L306
    LINENUMBER 642 L306
    ILOAD 26
    IFNE L307
    ALOAD 28
    GETSTATIC androidx/compose/runtime/Composer.Companion : Landroidx/compose/runtime/Composer$Companion;
    INVOKEVIRTUAL androidx/compose/runtime/Composer$Companion.getEmpty ()Ljava/lang/Object;
    IF_ACMPNE L308
   L307
    LINENUMBER 643 L307
    NOP
   L309
    ICONST_0
    ISTORE 30
   L310
    LINENUMBER 528 L310
    ALOAD 10
    INVOKEDYNAMIC invoke(Landroidx/compose/runtime/MutableState;)Lkotlin/jvm/functions/Function0; [
      // handle kind 0x6 : INVOKESTATIC
      java/lang/invoke/LambdaMetafactory.metafactory(Ljava/lang/invoke/MethodHandles$Lookup;Ljava/lang/String;Ljava/lang/invoke/MethodType;Ljava/lang/invoke/MethodType;Ljava/lang/invoke/MethodHandle;Ljava/lang/invoke/MethodType;)Ljava/lang/invoke/CallSite;
      // arguments:
      ()Ljava/lang/Object;, 
      // handle kind 0x6 : INVOKESTATIC
      com/codzuregroup/daycall/ui/alarm/EditAlarmScreenKt.EditAlarmScreen$lambda$33$lambda$32(Landroidx/compose/runtime/MutableState;)Lkotlin/Unit;, 
      ()Lkotlin/Unit;
    ]
    NOP
    GOTO L311
   L311
   L312
    LINENUMBER 643 L312
    ASTORE 31
   L313
    LINENUMBER 644 L313
    ALOAD 25
    ALOAD 31
    INVOKEINTERFACE androidx/compose/runtime/Composer.updateRememberedValue (Ljava/lang/Object;)V (itf)
   L314
    LINENUMBER 645 L314
    ALOAD 31
   L315
    GOTO L316
   L308
    LINENUMBER 646 L308
    ALOAD 28
   L316
    LINENUMBER 642 L316
    NOP
   L317
    LINENUMBER 641 L317
    NOP
   L318
    LINENUMBER 641 L318
    NOP
    GOTO L319
   L319
    LINENUMBER 528 L319
    CHECKCAST kotlin/jvm/functions/Function0
    ASTORE 24
   L320
    ALOAD 6
    INVOKEINTERFACE androidx/compose/runtime/Composer.endReplaceGroup ()V (itf)
    ALOAD 24
   L321
    LINENUMBER 542 L321
    LDC 1132839942
    NOP
    ICONST_1
    NEW com/codzuregroup/daycall/ui/alarm/EditAlarmScreenKt$EditAlarmScreen$9
    DUP
    ALOAD 5
    ALOAD 17
    ALOAD 10
    INVOKESPECIAL com/codzuregroup/daycall/ui/alarm/EditAlarmScreenKt$EditAlarmScreen$9.<init> (Lkotlin/jvm/functions/Function1;Landroidx/compose/runtime/MutableState;Landroidx/compose/runtime/MutableState;)V
    ALOAD 6
    BIPUSH 54
    INVOKESTATIC androidx/compose/runtime/internal/ComposableLambdaKt.rememberComposableLambda (IZLjava/lang/Object;Landroidx/compose/runtime/Composer;I)Landroidx/compose/runtime/internal/ComposableLambda;
    CHECKCAST kotlin/jvm/functions/Function2
    ACONST_NULL
   L322
    LINENUMBER 557 L322
    LDC -274886008
    NOP
    ICONST_1
    NEW com/codzuregroup/daycall/ui/alarm/EditAlarmScreenKt$EditAlarmScreen$10
    DUP
    ALOAD 10
    INVOKESPECIAL com/codzuregroup/daycall/ui/alarm/EditAlarmScreenKt$EditAlarmScreen$10.<init> (Landroidx/compose/runtime/MutableState;)V
    ALOAD 6
    BIPUSH 54
    INVOKESTATIC androidx/compose/runtime/internal/ComposableLambdaKt.rememberComposableLambda (IZLjava/lang/Object;Landroidx/compose/runtime/Composer;I)Landroidx/compose/runtime/internal/ComposableLambda;
    CHECKCAST kotlin/jvm/functions/Function2
    ACONST_NULL
    GETSTATIC com/codzuregroup/daycall/ui/alarm/ComposableSingletons$EditAlarmScreenKt.INSTANCE : Lcom/codzuregroup/daycall/ui/alarm/ComposableSingletons$EditAlarmScreenKt;
    INVOKEVIRTUAL com/codzuregroup/daycall/ui/alarm/ComposableSingletons$EditAlarmScreenKt.getLambda-18$app_samsungDebug ()Lkotlin/jvm/functions/Function2;
    GETSTATIC com/codzuregroup/daycall/ui/alarm/ComposableSingletons$EditAlarmScreenKt.INSTANCE : Lcom/codzuregroup/daycall/ui/alarm/ComposableSingletons$EditAlarmScreenKt;
    INVOKEVIRTUAL com/codzuregroup/daycall/ui/alarm/ComposableSingletons$EditAlarmScreenKt.getLambda-19$app_samsungDebug ()Lkotlin/jvm/functions/Function2;
    ACONST_NULL
    LCONST_0
    LCONST_0
    LCONST_0
    LCONST_0
    FCONST_0
    ACONST_NULL
    ALOAD 6
    LDC 1772598
    ICONST_0
    SIPUSH 16276
   L323
    LINENUMBER 527 L323
    INVOKESTATIC androidx/compose/material3/AndroidAlertDialog_androidKt.AlertDialog-Oix01E0 (Lkotlin/jvm/functions/Function0;Lkotlin/jvm/functions/Function2;Landroidx/compose/ui/Modifier;Lkotlin/jvm/functions/Function2;Lkotlin/jvm/functions/Function2;Lkotlin/jvm/functions/Function2;Lkotlin/jvm/functions/Function2;Landroidx/compose/ui/graphics/Shape;JJJJFLandroidx/compose/ui/window/DialogProperties;Landroidx/compose/runtime/Composer;III)V
   L301
    INVOKESTATIC androidx/compose/runtime/ComposerKt.isTraceInProgress ()Z
    IFEQ L324
    INVOKESTATIC androidx/compose/runtime/ComposerKt.traceEventEnd ()V
   L324
    GOTO L325
   L19
    LINENUMBER 566 L19
    ALOAD 6
    INVOKEINTERFACE androidx/compose/runtime/Composer.skipToGroupEnd ()V (itf)
   L325
    ALOAD 6
    INVOKEINTERFACE androidx/compose/runtime/Composer.endRestartGroup ()Landroidx/compose/runtime/ScopeUpdateScope; (itf)
    ASTORE 9
   L326
    ALOAD 9
    IFNULL L327
    ALOAD 9
    INVOKESTATIC kotlin/jvm/internal/$PseudoInsn.AS_NOT_NULL (Ljava/lang/Object;)Ljava/lang/Object;
    ASTORE 9
    ALOAD 9
    LLOAD 0
    ALOAD 2
    ALOAD 3
    ALOAD 4
    ALOAD 5
    ILOAD 7
    INVOKEDYNAMIC invoke(JLcom/codzuregroup/daycall/ui/AlarmViewModel;Lkotlin/jvm/functions/Function0;Lkotlin/jvm/functions/Function1;Lkotlin/jvm/functions/Function1;I)Lkotlin/jvm/functions/Function2; [
      // handle kind 0x6 : INVOKESTATIC
      java/lang/invoke/LambdaMetafactory.metafactory(Ljava/lang/invoke/MethodHandles$Lookup;Ljava/lang/String;Ljava/lang/invoke/MethodType;Ljava/lang/invoke/MethodType;Ljava/lang/invoke/MethodHandle;Ljava/lang/invoke/MethodType;)Ljava/lang/invoke/CallSite;
      // arguments:
      (Ljava/lang/Object;Ljava/lang/Object;)Ljava/lang/Object;, 
      // handle kind 0x6 : INVOKESTATIC
      com/codzuregroup/daycall/ui/alarm/EditAlarmScreenKt.EditAlarmScreen$lambda$34(JLcom/codzuregroup/daycall/ui/AlarmViewModel;Lkotlin/jvm/functions/Function0;Lkotlin/jvm/functions/Function1;Lkotlin/jvm/functions/Function1;ILandroidx/compose/runtime/Composer;I)Lkotlin/Unit;, 
      (Landroidx/compose/runtime/Composer;Ljava/lang/Integer;)Lkotlin/Unit;
    ]
    INVOKEINTERFACE androidx/compose/runtime/ScopeUpdateScope.updateScope (Lkotlin/jvm/functions/Function2;)V (itf)
    GOTO L328
   L329
    NOP
   L328
    NOP
    RETURN
   L330
   L327
    ACONST_NULL
    ASTORE 9
    GOTO L329
    LOCALVARIABLE $i$a$-cache-EditAlarmScreenKt$EditAlarmScreen$showTimePicker$2\3\570\0 I L29 L30 16
    LOCALVARIABLE value\2 Ljava/lang/Object; L32 L34 16
    LOCALVARIABLE $i$a$-let-ComposerKt$cache$1\2\568\1 I L25 L36 15
    LOCALVARIABLE it\1 Ljava/lang/Object; L24 L36 14
    LOCALVARIABLE $i$f$cache\1\78 I L23 L38 13
    LOCALVARIABLE $this$cache\1 Landroidx/compose/runtime/Composer; L22 L38 11
    LOCALVARIABLE invalid\1 Z L22 L38 12
    LOCALVARIABLE $i$a$-cache-EditAlarmScreenKt$EditAlarmScreen$showDeleteDialog$2\6\576\0 I L50 L51 17
    LOCALVARIABLE value\5 Ljava/lang/Object; L53 L55 17
    LOCALVARIABLE $i$a$-let-ComposerKt$cache$1\5\574\4 I L46 L57 16
    LOCALVARIABLE it\4 Ljava/lang/Object; L45 L57 15
    LOCALVARIABLE $i$f$cache\4\79 I L44 L59 14
    LOCALVARIABLE $this$cache\4 Landroidx/compose/runtime/Composer; L43 L59 12
    LOCALVARIABLE invalid\4 Z L43 L59 13
    LOCALVARIABLE $i$a$-cache-EditAlarmScreenKt$EditAlarmScreen$selectedHour$2\9\582\0 I L71 L72 18
    LOCALVARIABLE value\8 Ljava/lang/Object; L74 L76 18
    LOCALVARIABLE $i$a$-let-ComposerKt$cache$1\8\580\7 I L67 L78 17
    LOCALVARIABLE it\7 Ljava/lang/Object; L66 L78 16
    LOCALVARIABLE $i$f$cache\7\80 I L65 L80 15
    LOCALVARIABLE $this$cache\7 Landroidx/compose/runtime/Composer; L64 L80 13
    LOCALVARIABLE invalid\7 Z L64 L80 14
    LOCALVARIABLE $i$a$-cache-EditAlarmScreenKt$EditAlarmScreen$selectedMinute$2\12\588\0 I L92 L93 19
    LOCALVARIABLE value\11 Ljava/lang/Object; L95 L97 19
    LOCALVARIABLE $i$a$-let-ComposerKt$cache$1\11\586\10 I L88 L99 18
    LOCALVARIABLE it\10 Ljava/lang/Object; L87 L99 17
    LOCALVARIABLE $i$f$cache\10\81 I L86 L101 16
    LOCALVARIABLE $this$cache\10 Landroidx/compose/runtime/Composer; L85 L101 14
    LOCALVARIABLE invalid\10 Z L85 L101 15
    LOCALVARIABLE $i$a$-cache-EditAlarmScreenKt$EditAlarmScreen$alarmLabel$2\15\594\0 I L113 L114 20
    LOCALVARIABLE value\14 Ljava/lang/Object; L116 L118 20
    LOCALVARIABLE $i$a$-let-ComposerKt$cache$1\14\592\13 I L109 L120 19
    LOCALVARIABLE it\13 Ljava/lang/Object; L108 L120 18
    LOCALVARIABLE $i$f$cache\13\82 I L107 L122 17
    LOCALVARIABLE $this$cache\13 Landroidx/compose/runtime/Composer; L106 L122 15
    LOCALVARIABLE invalid\13 Z L106 L122 16
    LOCALVARIABLE $i$a$-cache-EditAlarmScreenKt$EditAlarmScreen$selectedSound$2\18\600\0 I L134 L135 21
    LOCALVARIABLE value\17 Ljava/lang/Object; L137 L139 21
    LOCALVARIABLE $i$a$-let-ComposerKt$cache$1\17\598\16 I L130 L141 20
    LOCALVARIABLE it\16 Ljava/lang/Object; L129 L141 19
    LOCALVARIABLE $i$f$cache\16\83 I L128 L143 18
    LOCALVARIABLE $this$cache\16 Landroidx/compose/runtime/Composer; L127 L143 16
    LOCALVARIABLE invalid\16 Z L127 L143 17
    LOCALVARIABLE $i$a$-cache-EditAlarmScreenKt$EditAlarmScreen$selectedVibe$2\21\606\0 I L155 L156 22
    LOCALVARIABLE value\20 Ljava/lang/Object; L158 L160 22
    LOCALVARIABLE $i$a$-let-ComposerKt$cache$1\20\604\19 I L151 L162 21
    LOCALVARIABLE it\19 Ljava/lang/Object; L150 L162 20
    LOCALVARIABLE $i$f$cache\19\84 I L149 L164 19
    LOCALVARIABLE $this$cache\19 Landroidx/compose/runtime/Composer; L148 L164 17
    LOCALVARIABLE invalid\19 Z L148 L164 18
    LOCALVARIABLE $i$a$-cache-EditAlarmScreenKt$EditAlarmScreen$isEnabled$2\24\612\0 I L176 L177 23
    LOCALVARIABLE value\23 Ljava/lang/Object; L179 L181 23
    LOCALVARIABLE $i$a$-let-ComposerKt$cache$1\23\610\22 I L172 L183 22
    LOCALVARIABLE it\22 Ljava/lang/Object; L171 L183 21
    LOCALVARIABLE $i$f$cache\22\85 I L170 L185 20
    LOCALVARIABLE $this$cache\22 Landroidx/compose/runtime/Composer; L169 L185 18
    LOCALVARIABLE invalid\22 Z L169 L185 19
    LOCALVARIABLE $i$a$-cache-EditAlarmScreenKt$EditAlarmScreen$currentAlarm$2\27\618\0 I L197 L198 24
    LOCALVARIABLE value\26 Ljava/lang/Object; L200 L202 24
    LOCALVARIABLE $i$a$-let-ComposerKt$cache$1\26\616\25 I L193 L204 23
    LOCALVARIABLE it\25 Ljava/lang/Object; L192 L204 22
    LOCALVARIABLE $i$f$cache\25\86 I L191 L206 21
    LOCALVARIABLE $this$cache\25 Landroidx/compose/runtime/Composer; L190 L206 19
    LOCALVARIABLE invalid\25 Z L190 L206 20
    LOCALVARIABLE $i$f$getCurrent\28\88 I L211 L213 21
    LOCALVARIABLE this_\28 Landroidx/compose/runtime/CompositionLocal; L210 L213 19
    LOCALVARIABLE $changed\28 I L210 L213 20
    LOCALVARIABLE $i$a$-cache-EditAlarmScreenKt$EditAlarmScreen$settingsManager$1\31\625\0 I L223 L224 26
    LOCALVARIABLE value\30 Ljava/lang/Object; L226 L228 27
    LOCALVARIABLE $i$a$-let-ComposerKt$cache$1\30\623\29 I L219 L230 25
    LOCALVARIABLE it\29 Ljava/lang/Object; L218 L230 24
    LOCALVARIABLE $i$f$cache\29\89 I L217 L232 23
    LOCALVARIABLE $this$cache\29 Landroidx/compose/runtime/Composer; L216 L232 21
    LOCALVARIABLE invalid\29 Z L216 L232 22
    LOCALVARIABLE $i$a$-cache-EditAlarmScreenKt$EditAlarmScreen$1\34\631\0 I L255 L256 30
    LOCALVARIABLE value\33 Ljava/lang/Object; L258 L260 31
    LOCALVARIABLE $i$a$-let-ComposerKt$cache$1\33\629\32 I L251 L262 29
    LOCALVARIABLE it\32 Ljava/lang/Object; L250 L262 28
    LOCALVARIABLE $i$f$cache\32\101 I L249 L264 27
    LOCALVARIABLE $this$cache\32 Landroidx/compose/runtime/Composer; L248 L264 25
    LOCALVARIABLE invalid\32 Z L248 L264 26
    LOCALVARIABLE $i$a$-cache-EditAlarmScreenKt$EditAlarmScreen$4\37\637\0 I L285 L286 30
    LOCALVARIABLE value\36 Ljava/lang/Object; L288 L290 31
    LOCALVARIABLE $i$a$-let-ComposerKt$cache$1\36\635\35 I L281 L292 29
    LOCALVARIABLE it\35 Ljava/lang/Object; L280 L292 28
    LOCALVARIABLE $i$f$cache\35\467 I L279 L294 27
    LOCALVARIABLE $this$cache\35 Landroidx/compose/runtime/Composer; L278 L294 25
    LOCALVARIABLE invalid\35 Z L278 L294 26
    LOCALVARIABLE $i$a$-cache-EditAlarmScreenKt$EditAlarmScreen$8\40\643\0 I L310 L311 30
    LOCALVARIABLE value\39 Ljava/lang/Object; L313 L315 31
    LOCALVARIABLE $i$a$-let-ComposerKt$cache$1\39\641\38 I L306 L317 29
    LOCALVARIABLE it\38 Ljava/lang/Object; L305 L317 28
    LOCALVARIABLE $i$f$cache\38\528 I L304 L319 27
    LOCALVARIABLE $this$cache\38 Landroidx/compose/runtime/Composer; L303 L319 25
    LOCALVARIABLE invalid\38 Z L303 L319 26
    LOCALVARIABLE showTimePicker$delegate Landroidx/compose/runtime/MutableState; L41 L324 9
    LOCALVARIABLE showDeleteDialog$delegate Landroidx/compose/runtime/MutableState; L62 L324 10
    LOCALVARIABLE selectedHour$delegate Landroidx/compose/runtime/MutableState; L83 L324 11
    LOCALVARIABLE selectedMinute$delegate Landroidx/compose/runtime/MutableState; L104 L324 12
    LOCALVARIABLE alarmLabel$delegate Landroidx/compose/runtime/MutableState; L125 L324 13
    LOCALVARIABLE selectedSound$delegate Landroidx/compose/runtime/MutableState; L146 L324 14
    LOCALVARIABLE selectedVibe$delegate Landroidx/compose/runtime/MutableState; L167 L324 15
    LOCALVARIABLE isEnabled$delegate Landroidx/compose/runtime/MutableState; L188 L324 16
    LOCALVARIABLE currentAlarm$delegate Landroidx/compose/runtime/MutableState; L209 L324 17
    LOCALVARIABLE context Landroid/content/Context; L214 L324 18
    LOCALVARIABLE settingsManager Lcom/codzuregroup/daycall/ui/settings/SettingsManager; L235 L324 19
    LOCALVARIABLE timeFormat$delegate Landroidx/compose/runtime/State; L236 L324 20
    LOCALVARIABLE timeFormatter Ljava/time/format/DateTimeFormatter; L243 L324 21
    LOCALVARIABLE periodFormatter Ljava/time/format/DateTimeFormatter; L244 L324 22
    LOCALVARIABLE selectedTime Ljava/time/LocalTime; L245 L324 23
    LOCALVARIABLE $dirty I L2 L330 8
    LOCALVARIABLE alarmId J L0 L330 0
    LOCALVARIABLE viewModel Lcom/codzuregroup/daycall/ui/AlarmViewModel; L0 L330 2
    LOCALVARIABLE onBackPressed Lkotlin/jvm/functions/Function0; L0 L330 3
    LOCALVARIABLE onSaveAlarm Lkotlin/jvm/functions/Function1; L0 L330 4
    LOCALVARIABLE onDeleteAlarm Lkotlin/jvm/functions/Function1; L0 L330 5
    LOCALVARIABLE $composer Landroidx/compose/runtime/Composer; L0 L330 6
    LOCALVARIABLE $changed I L0 L330 7
    MAXSTACK = 28
    MAXLOCALS = 34

File is unknown
The root cause java.lang.OutOfMemoryError was thrown at: java.base/java.util.ArrayList.grow(ArrayList.java:240)
	at org.jetbrains.kotlin.codegen.TransformationMethodVisitor.visitEnd(TransformationMethodVisitor.kt:89)
	at org.jetbrains.org.objectweb.asm.MethodVisitor.visitEnd(MethodVisitor.java:783)
	at org.jetbrains.org.objectweb.asm.tree.MethodNode.accept(MethodNode.java:772)
	at org.jetbrains.kotlin.backend.jvm.codegen.ClassCodegen.generateMethod(ClassCodegen.kt:453)
	at org.jetbrains.kotlin.backend.jvm.codegen.ClassCodegen.generate(ClassCodegen.kt:168)
	at org.jetbrains.kotlin.backend.jvm.FileCodegen.lower(JvmPhases.kt:39)
	at org.jetbrains.kotlin.backend.common.phaser.PhaseFactoriesKt.createFilePhase$lambda$4(PhaseFactories.kt:71)
	at org.jetbrains.kotlin.backend.common.phaser.PhaseBuildersKt$createSimpleNamedCompilerPhase$1.phaseBody(PhaseBuilders.kt:69)
	at org.jetbrains.kotlin.backend.common.phaser.SimpleNamedCompilerPhase.phaseBody(CompilerPhase.kt:226)
	at org.jetbrains.kotlin.backend.common.phaser.AbstractNamedCompilerPhase.invoke(CompilerPhase.kt:113)
	at org.jetbrains.kotlin.backend.common.phaser.PerformByIrFilePhase.invokeSequential(performByIrFile.kt:62)
	at org.jetbrains.kotlin.backend.common.phaser.PerformByIrFilePhase.invoke(performByIrFile.kt:52)
	at org.jetbrains.kotlin.backend.common.phaser.PerformByIrFilePhase.invoke(performByIrFile.kt:38)
	at org.jetbrains.kotlin.backend.common.phaser.NamedCompilerPhase.phaseBody(CompilerPhase.kt:166)
	at org.jetbrains.kotlin.backend.common.phaser.AbstractNamedCompilerPhase.invoke(CompilerPhase.kt:113)
	at org.jetbrains.kotlin.backend.common.phaser.CompositePhase.invoke(PhaseBuilders.kt:27)
	at org.jetbrains.kotlin.backend.common.phaser.CompositePhase.invoke(PhaseBuilders.kt:14)
	at org.jetbrains.kotlin.backend.common.phaser.NamedCompilerPhase.phaseBody(CompilerPhase.kt:166)
	at org.jetbrains.kotlin.backend.common.phaser.AbstractNamedCompilerPhase.invoke(CompilerPhase.kt:113)
	at org.jetbrains.kotlin.backend.common.phaser.CompilerPhaseKt.invokeToplevel(CompilerPhase.kt:62)
	at org.jetbrains.kotlin.backend.jvm.JvmIrCodegenFactory.invokeCodegen(JvmIrCodegenFactory.kt:371)
	at org.jetbrains.kotlin.codegen.CodegenFactory.generateModule(CodegenFactory.kt:47)
	at org.jetbrains.kotlin.backend.jvm.JvmIrCodegenFactory.generateModuleInFrontendIRMode(JvmIrCodegenFactory.kt:433)
	at org.jetbrains.kotlin.cli.jvm.compiler.pipeline.JvmCompilerPipelineKt.generateCodeFromIr(jvmCompilerPipeline.kt:246)
	at org.jetbrains.kotlin.cli.jvm.compiler.pipeline.JvmCompilerPipelineKt.compileModulesUsingFrontendIrAndLightTree(jvmCompilerPipeline.kt:142)
	at org.jetbrains.kotlin.cli.jvm.K2JVMCompiler.doExecute(K2JVMCompiler.kt:148)
	at org.jetbrains.kotlin.cli.jvm.K2JVMCompiler.doExecute(K2JVMCompiler.kt:43)
	at org.jetbrains.kotlin.cli.common.CLICompiler.execImpl(CLICompiler.kt:103)
	at org.jetbrains.kotlin.cli.common.CLICompiler.execImpl(CLICompiler.kt:49)
	at org.jetbrains.kotlin.cli.common.CLITool.exec(CLITool.kt:101)
	at org.jetbrains.kotlin.incremental.IncrementalJvmCompilerRunner.runCompiler(IncrementalJvmCompilerRunner.kt:464)
	at org.jetbrains.kotlin.incremental.IncrementalJvmCompilerRunner.runCompiler(IncrementalJvmCompilerRunner.kt:73)
	at org.jetbrains.kotlin.incremental.IncrementalCompilerRunner.doCompile(IncrementalCompilerRunner.kt:506)
	at org.jetbrains.kotlin.incremental.IncrementalCompilerRunner.compileImpl(IncrementalCompilerRunner.kt:423)
	at org.jetbrains.kotlin.incremental.IncrementalCompilerRunner.compileNonIncrementally(IncrementalCompilerRunner.kt:301)
	at org.jetbrains.kotlin.incremental.IncrementalCompilerRunner.compile(IncrementalCompilerRunner.kt:129)
	at org.jetbrains.kotlin.daemon.CompileServiceImplBase.execIncrementalCompiler(CompileServiceImpl.kt:675)
	at org.jetbrains.kotlin.daemon.CompileServiceImplBase.access$execIncrementalCompiler(CompileServiceImpl.kt:92)
	at org.jetbrains.kotlin.daemon.CompileServiceImpl.compile(CompileServiceImpl.kt:1660)
	at java.base/jdk.internal.reflect.DirectMethodHandleAccessor.invoke(DirectMethodHandleAccessor.java:103)
	at java.base/java.lang.reflect.Method.invoke(Method.java:580)
	at java.rmi/sun.rmi.server.UnicastServerRef.dispatch(UnicastServerRef.java:360)
	at java.rmi/sun.rmi.transport.Transport$1.run(Transport.java:200)
	at java.rmi/sun.rmi.transport.Transport$1.run(Transport.java:197)
	at java.base/java.security.AccessController.doPrivileged(AccessController.java:714)
	at java.rmi/sun.rmi.transport.Transport.serviceCall(Transport.java:196)
	at java.rmi/sun.rmi.transport.tcp.TCPTransport.handleMessages(TCPTransport.java:598)
	at java.rmi/sun.rmi.transport.tcp.TCPTransport$ConnectionHandler.run0(TCPTransport.java:844)
	at java.rmi/sun.rmi.transport.tcp.TCPTransport$ConnectionHandler.lambda$run$0(TCPTransport.java:721)
	at java.base/java.security.AccessController.doPrivileged(AccessController.java:400)
	at java.rmi/sun.rmi.transport.tcp.TCPTransport$ConnectionHandler.run(TCPTransport.java:720)
	at java.base/java.util.concurrent.ThreadPoolExecutor.runWorker(ThreadPoolExecutor.java:1144)
	at java.base/java.util.concurrent.ThreadPoolExecutor$Worker.run(ThreadPoolExecutor.java:642)
	at java.base/java.lang.Thread.run(Thread.java:1575)
Caused by: java.lang.OutOfMemoryError: Java heap space
	at java.base/java.util.ArrayList.grow(ArrayList.java:240)
	at java.base/java.util.ArrayList.grow(ArrayList.java:245)
	at java.base/java.util.ArrayList.add(ArrayList.java:516)
	at org.jetbrains.org.objectweb.asm.tree.analysis.Frame.executeInvokeInsn(Frame.java:643)
	at org.jetbrains.org.objectweb.asm.tree.analysis.Frame.execute(Frame.java:573)
	at org.jetbrains.kotlin.codegen.optimization.common.FastAnalyzer.analyzeInstruction(FastAnalyzer.kt:111)
	at org.jetbrains.kotlin.codegen.optimization.common.FastAnalyzer.analyzeMainLoop(FastAnalyzer.kt:74)
	at org.jetbrains.kotlin.codegen.optimization.common.FastAnalyzer.analyze(FastAnalyzer.kt:53)
	at org.jetbrains.kotlin.codegen.optimization.transformer.MethodTransformer.analyze(MethodTransformer.java:49)
	at org.jetbrains.kotlin.codegen.optimization.nullCheck.RedundantNullCheckMethodTransformer$TransformerPass.analyzeNullabilities(RedundantNullCheckMethodTransformer.kt:65)
	at org.jetbrains.kotlin.codegen.optimization.nullCheck.RedundantNullCheckMethodTransformer$TransformerPass.run(RedundantNullCheckMethodTransformer.kt:55)
	at org.jetbrains.kotlin.codegen.optimization.nullCheck.RedundantNullCheckMethodTransformer.transform(RedundantNullCheckMethodTransformer.kt:43)
	at org.jetbrains.kotlin.codegen.optimization.transformer.CompositeMethodTransformer.transform(CompositeMethodTransformer.kt:25)
	at org.jetbrains.kotlin.codegen.optimization.OptimizationMethodVisitor.performTransformations(OptimizationMethodVisitor.kt:74)
	at org.jetbrains.kotlin.codegen.TransformationMethodVisitor.visitEnd(TransformationMethodVisitor.kt:67)
	at org.jetbrains.org.objectweb.asm.MethodVisitor.visitEnd(MethodVisitor.java:783)
	at org.jetbrains.org.objectweb.asm.tree.MethodNode.accept(MethodNode.java:772)
	at org.jetbrains.kotlin.backend.jvm.codegen.ClassCodegen.generateMethod(ClassCodegen.kt:453)
	at org.jetbrains.kotlin.backend.jvm.codegen.ClassCodegen.generate(ClassCodegen.kt:168)
	at org.jetbrains.kotlin.backend.jvm.FileCodegen.lower(JvmPhases.kt:39)
	at org.jetbrains.kotlin.backend.common.phaser.PhaseFactoriesKt.createFilePhase$lambda$4(PhaseFactories.kt:71)
	at org.jetbrains.kotlin.backend.common.phaser.PhaseFactoriesKt$$Lambda/0x000007f80115e168.invoke(Unknown Source)
	at org.jetbrains.kotlin.backend.common.phaser.PhaseBuildersKt$createSimpleNamedCompilerPhase$1.phaseBody(PhaseBuilders.kt:69)
	at org.jetbrains.kotlin.backend.common.phaser.SimpleNamedCompilerPhase.phaseBody(CompilerPhase.kt:226)
	at org.jetbrains.kotlin.backend.common.phaser.AbstractNamedCompilerPhase.invoke(CompilerPhase.kt:113)
	at org.jetbrains.kotlin.backend.common.phaser.PerformByIrFilePhase.invokeSequential(performByIrFile.kt:62)
	at org.jetbrains.kotlin.backend.common.phaser.PerformByIrFilePhase.invoke(performByIrFile.kt:52)
	at org.jetbrains.kotlin.backend.common.phaser.PerformByIrFilePhase.invoke(performByIrFile.kt:38)
	at org.jetbrains.kotlin.backend.common.phaser.NamedCompilerPhase.phaseBody(CompilerPhase.kt:166)
	at org.jetbrains.kotlin.backend.common.phaser.AbstractNamedCompilerPhase.invoke(CompilerPhase.kt:113)
	at org.jetbrains.kotlin.backend.common.phaser.CompositePhase.invoke(PhaseBuilders.kt:27)
	at org.jetbrains.kotlin.backend.common.phaser.CompositePhase.invoke(PhaseBuilders.kt:14)


